{
    "主條目": {
        "content": [
            {
                "備考": "",
                "土地坐落": {
                    "地號": "662",
                    "小段": "七",
                    "段": "寶清",
                    "編號": "1",
                    "縣市": "臺北市",
                    "鄉鎮市區": "松山區"
                },
                "地目": "建",
                "最低拍賣價格": "1,800,000元",
                "權利範圍": "100000分之21",
                "面積平方公尺": "1233.00"
            }
        ]
    },
    "細條目": {
        "content": [
            {
                "備考": "含共同使用部分1593建號之持分",
                "基地坐落": "臺北市松山區寶清段七小段662地號",
                "建物門牌": "八德路四段678號地下",
                "建物面積": {
                    "樓層面積": {
                        "合計": "785.63",
                        "樓層面積": "一層：17.24騎樓：7.64地下一層：760.75",
                        "附屬建物主要建築材料及用途": ""
                    }
                },
                "建築式樣主要建築材料": "臺北市松山區寶清段七小段662地號--------------八德路四段678號地下",
                "建號": "1591",
                "房屋層數": "12層鋼筋混凝土造",
                "最低拍賣價格": "1,320,000元",
                "權利範圍": "10000分之252"
            }
        ],
        "使用情形": "本件據台北新站大樓社區總幹事稱於民國88年納莉風災後，地下室淹水至天花板，鐵捲門無法開啟，\n現無人得進出使用。因係拍賣應有部分，拍定後不點交，建物共有人有優先承買權。\n",
        "備註": "一、上開不動產2宗合併拍賣，請投標人分別出價。\n二、拍賣最低價額合計新台幣：3,120,000元，以總價最高者得標。\n三、保證金新台幣：630,000元。\n",
        "點交情形": "點交否：不點交"
    }
}