{
    "主條目": {
        "content": [
            {
                "備考": "",
                "土地坐落": {
                    "地號": "181",
                    "小段": "一",
                    "段": "三興",
                    "編號": "1",
                    "縣市": "臺北市",
                    "鄉鎮市區": "信義區"
                },
                "地目": "建",
                "最低拍賣價格": "19,000,000元",
                "權利範圍": "4分之1",
                "面積平方公尺": "120"
            }
        ]
    },
    "細條目": {
        "content": [
            {
                "備考": "",
                "基地坐落": "臺北市信義區三興段一小段181地號",
                "建物門牌": "臺北市信義區莊敬路202號4樓",
                "建物面積": {
                    "樓層面積": {
                        "合計": "84.79",
                        "樓層面積": "四層：79.3陽台：5.49",
                        "附屬建物主要建築材料及用途": ""
                    }
                },
                "建築式樣主要建築材料": "臺北市信義區三興段一小段181地號--------------臺北市信義區莊敬路202號4樓",
                "建號": "409",
                "房屋層數": "4樓鋼筋混凝土造",
                "最低拍賣價格": "2,030,000元",
                "權利範圍": "全部"
            },
            {
                "備考": "",
                "基地坐落": "臺北市信義區三興段一小段181地號",
                "建物門牌": "臺北市信義區莊敬路202號4樓頂層增建部分",
                "建物面積": {
                    "樓層面積": {
                        "合計": "79.54",
                        "樓層面積": "第四層頂層增建部分：79.54",
                        "附屬建物主要建築材料及用途": ""
                    }
                },
                "建築式樣主要建築材料": "臺北市信義區三興段一小段181地號--------------臺北市信義區莊敬路202號4樓頂層增建部分",
                "建號": "5547",
                "房屋層數": "空白",
                "最低拍賣價格": "1,070,000元",
                "權利範圍": "全部"
            }
        ],
        "使用情形": "一、本件拍賣標的據本院現場履勘，現由債務人將其隔間出租，除債務人自己居住使用其中一房外，\n其餘則以每月八千至九千元不等之租金出租予第三人，故本件拍定後除債務人自己居住之房間點\n交外，其餘部分不點交，租賃關係須拍定人自行解決。\n二、本件拍賣標的於查封時經詢在場債務人，除增建部分即5547建號建物有漏水情形外，其餘無海砂\n屋、輻射屋、地震或火災受創及建物內有非自然死亡等足以影響交易之特殊情事。又依臺北市建\n築管理工程處105.04.19北市都建查字第10567004400號函覆，本件拍賣標的5547建號建物係垂直\n增建違章建築，屬既存違章建築，已列入分類分期處理，列管拆除，故拍定人須自行負擔被拆除\n之風險，請應買人注意。\n三、再5547建號建物因未辦理建築物所有權第一次登記，拍定後無法逕持不動產權利移轉證書辦理所\n有權移轉登記，亦請應買人注意。\n",
        "備註": "一、上開不動產3宗合併拍賣，請投標人分別出價。\n二、拍賣最低價額合計新台幣：22,100,000元，以總價最高者得標。\n三、保證金新台幣：4,420,000元。\n四、抵押權拍定後均塗銷。\n",
        "點交情形": "點交否：部分點交、部分不點交"
    }
}